knitj/__init__.py
knitj/cell.py
knitj/cli.py
knitj/client/.eslintrc
knitj/client/.gitignore
knitj/client/package-lock.json
knitj/client/package.json
knitj/client/static/client.js
knitj/client/templates/index.html
knitj/convert.py
knitj/document.py
knitj/jupyter_messaging/__init__.py
knitj/jupyter_messaging/content/__init__.py
knitj/jupyter_messaging/content/content.py
knitj/jupyter_messaging/message.py
knitj/kernel.py
knitj/parser.py
knitj/server.py
knitj/source.py
knitj/webserver.py
knitj-0.3.1.dist-info/entry_points.txt
knitj-0.3.1.dist-info/LICENSE
knitj-0.3.1.dist-info/WHEEL
knitj-0.3.1.dist-info/METADATA
knitj-0.3.1.dist-info/RECORD
